{
    "version": 1,
    "type": "pokemon",
    "name": "dewgong",
    "nationalDex": 87,
    "ifDex": 87,
    "types": [
        {
            "slot": 1,
            "type": "water"
        },
        {
            "slot": 2,
            "type": "ice"
        }
    ],
    "stats": {
        "hp": 90,
        "attack": 70,
        "defense": 80,
        "specialAttack": 70,
        "specialDefense": 95,
        "speed": 70
    },
    "abilities": [
        {
            "slot": 1,
            "ability": "thick-fat"
        },
        {
            "slot": 2,
            "ability": "hydration"
        },
        {
            "slot": "hidden",
            "ability": "ice-body"
        }
    ],
    "moves": {
        "levelup": [
            {
                "name": "sheer-cold",
                "learn_method": "levelup",
                "level": 0
            },
            {
                "name": "growl",
                "learn_method": "levelup",
                "level": 1
            },
            {
                "name": "headbutt",
                "learn_method": "levelup",
                "level": 1
            },
            {
                "name": "icy-wind",
                "learn_method": "levelup",
                "level": 1
            },
            {
                "name": "signal-beam",
                "learn_method": "levelup",
                "level": 1
            },
            {
                "name": "encore",
                "learn_method": "levelup",
                "level": 13
            },
            {
                "name": "ice-shard",
                "learn_method": "levelup",
                "level": 17
            },
            {
                "name": "rest",
                "learn_method": "levelup",
                "level": 21
            },
            {
                "name": "aqua-ring",
                "learn_method": "levelup",
                "level": 23
            },
            {
                "name": "aurora-beam",
                "learn_method": "levelup",
                "level": 27
            },
            {
                "name": "aqua-jet",
                "learn_method": "levelup",
                "level": 31
            },
            {
                "name": "brine",
                "learn_method": "levelup",
                "level": 33
            },
            {
                "name": "take-down",
                "learn_method": "levelup",
                "level": 39
            },
            {
                "name": "dive",
                "learn_method": "levelup",
                "level": 45
            },
            {
                "name": "aqua-tail",
                "learn_method": "levelup",
                "level": 49
            },
            {
                "name": "ice-beam",
                "learn_method": "levelup",
                "level": 55
            },
            {
                "name": "safeguard",
                "learn_method": "levelup",
                "level": 61
            },
            {
                "name": "hail",
                "learn_method": "levelup",
                "level": 65
            }
        ],
        "machine": [
            {
                "name": "surf",
                "learn_method": "machine",
                "tm_id": "hm03"
            },
            {
                "name": "waterfall",
                "learn_method": "machine",
                "tm_id": "hm05"
            },
            {
                "name": "dive",
                "learn_method": "machine",
                "tm_id": "hm06"
            },
            {
                "name": "toxic",
                "learn_method": "machine",
                "tm_id": "tm06"
            },
            {
                "name": "hail",
                "learn_method": "machine",
                "tm_id": "tm07"
            },
            {
                "name": "hidden-power",
                "learn_method": "machine",
                "tm_id": "tm10"
            },
            {
                "name": "aqua-jet",
                "learn_method": "machine",
                "tm_id": "tm105"
            },
            {
                "name": "smart-strike",
                "learn_method": "machine",
                "tm_id": "tm117"
            },
            {
                "name": "ice-beam",
                "learn_method": "machine",
                "tm_id": "tm13"
            },
            {
                "name": "blizzard",
                "learn_method": "machine",
                "tm_id": "tm14"
            },
            {
                "name": "hyper-beam",
                "learn_method": "machine",
                "tm_id": "tm15"
            },
            {
                "name": "protect",
                "learn_method": "machine",
                "tm_id": "tm17"
            },
            {
                "name": "rain-dance",
                "learn_method": "machine",
                "tm_id": "tm18"
            },
            {
                "name": "safeguard",
                "learn_method": "machine",
                "tm_id": "tm20"
            },
            {
                "name": "frustration",
                "learn_method": "machine",
                "tm_id": "tm21"
            },
            {
                "name": "return",
                "learn_method": "machine",
                "tm_id": "tm27"
            },
            {
                "name": "double-team",
                "learn_method": "machine",
                "tm_id": "tm32"
            },
            {
                "name": "facade",
                "learn_method": "machine",
                "tm_id": "tm42"
            },
            {
                "name": "rest",
                "learn_method": "machine",
                "tm_id": "tm44"
            },
            {
                "name": "attract",
                "learn_method": "machine",
                "tm_id": "tm45"
            },
            {
                "name": "thief",
                "learn_method": "machine",
                "tm_id": "tm46"
            },
            {
                "name": "round",
                "learn_method": "machine",
                "tm_id": "tm48"
            },
            {
                "name": "echoed-voice",
                "learn_method": "machine",
                "tm_id": "tm49"
            },
            {
                "name": "water-pulse",
                "learn_method": "machine",
                "tm_id": "tm55"
            },
            {
                "name": "fling",
                "learn_method": "machine",
                "tm_id": "tm56"
            },
            {
                "name": "giga-impact",
                "learn_method": "machine",
                "tm_id": "tm68"
            },
            {
                "name": "frost-breath",
                "learn_method": "machine",
                "tm_id": "tm79"
            },
            {
                "name": "swagger",
                "learn_method": "machine",
                "tm_id": "tm87"
            },
            {
                "name": "sleep-talk",
                "learn_method": "machine",
                "tm_id": "tm88"
            },
            {
                "name": "substitute",
                "learn_method": "machine",
                "tm_id": "tm90"
            }
        ],
        "tutor": [
            {
                "name": "drill-run",
                "learn_method": "tutor"
            },
            {
                "name": "iron-tail",
                "learn_method": "tutor"
            },
            {
                "name": "signal-beam",
                "learn_method": "tutor"
            }
        ],
        "egg": []
    }
}